MANIFEST.in
README.md
setup.cfg
setup.py
cjwparse/__init__.py
cjwparse/_util.py
cjwparse/api.py
cjwparse/csv.py
cjwparse/excel.py
cjwparse/json.py
cjwparse/mime.py
cjwparse/postprocess.py
cjwparse/settings.py
cjwparse/text.py
cjwparse.egg-info/PKG-INFO
cjwparse.egg-info/SOURCES.txt
cjwparse.egg-info/dependency_links.txt
cjwparse.egg-info/requires.txt
cjwparse.egg-info/top_level.txt
cjwparse.egg-info/zip-safe
cjwparse/i18n/__init__.py
cjwparse/i18n/_deprecated_i18n_messages.py
cjwparse/i18n/el.po
cjwparse/i18n/en.po
cjwparse/testing/__init__.py
cjwparse/testing/i18n.py