Metadata-Version: 2.1
Name: cjwparse
Version: 1.1.0
Summary: Utilities to help build Workbench modules
Home-page: http://github.com/CJWorkbench/cjwparse/
Author: Adam Hooper
Author-email: adam@adamhooper.com
License: MIT
Platform: UNKNOWN
Provides-Extra: tests
Provides-Extra: maintenance
